{"n-gramas":{"0":"i","1":"a","2":"u","3":"n","4":"t","5":"r","6":"l","7":"s","8":"d","9":"c","10":"o","11":"e","12":"p","13":"\u00e0","14":"m","15":"h","16":"\u2019","17":"g","18":"\u00e8","19":"z","20":"di","21":"v","22":"li","23":"ri","24":"ar","25":"ti","26":"ni","27":"ic","28":"is","29":"it","30":"un","31":"in","32":"na","33":"f","34":"tu","35":"cu","36":"ia","37":"on","38":"si","39":"b","40":"tt","41":"id","42":"al","43":"ch","44":"ip","45":"so","46":"ir","47":"ll","48":"el","49":"j","50":"\u00f9","51":"nd","52":"pa","53":"du","54":"nt","55":"zi","56":"lu","57":"rt","58":"ul","59":"io","60":"ta","61":"ci","62":"ut","63":"\u2019e","64":"iu","65":"ra","66":"nu","67":"ud","68":"at","69":"es","70":"as","71":"iri","72":"ad","73":"t\u00e0","74":"\u00ec","75":"sa","76":"en","77":"vi","78":"il","79":"us","80":"ii","81":"mi","82":"\u00e0d","83":"ma","84":"pr","85":"ap","86":"i\u00e8","87":"oni","88":"ell","89":"su","90":"uc","91":"tr","92":"\u00f2","93":"da","94":"ur","95":"h\u2019","96":"im","97":"la","98":"gn","99":"ss","100":"l\u2019","101":"ca","102":"tti","103":"ui","104":"an","105":"rit","106":"st","107":"itt","108":"up","109":"ali","110":"az","111":"ua","112":"icu","113":"una","114":"par","115":"tic","116":"ttu","117":"ch\u2019","118":"ru","119":"idi","120":"pi","121":"zio","122":"ac","123":"er","124":"dir","125":"q","126":"aa","127":"hj","128":"u\u00e0","129":"mu","130":"ig","131":"te","132":"\u2019a","133":"sc","134":"ulu","135":"\u2019el","136":"d\u2019","137":"um","138":"od","139":"\u00e0i","140":"azi","141":"it\u00e0","142":"iv","143":"uu","144":"me","145":"am","146":"iz","147":"or","148":"h\u00e8","149":"i\u00e0","150":"ib","151":"av","152":"og","153":"\u00e0a","154":"h\u2019e","155":"gh","156":"lla","157":"nip","158":"pu","159":"va","160":"re","161":"uo","162":"rti","163":"nz","164":"rs","165":"ion","166":"\u00e0u","167":"u\u00e8","168":"lt","169":"udi","170":"ars","171":"gl","172":"iun","173":"tut","174":"h\u00e0","175":"\u00e0di","176":"are","177":"be","178":"ich","179":"uin","180":"h\u00e0d","181":"h\u00ec","182":"cul","183":"art","184":"\u00e0c","185":"mo","186":"ja","187":"uh","188":"il\u2019","189":"sci","190":"nl","191":"if","192":"dil","193":"ial","194":"om","195":"sid","196":"ogn","197":"p\u00e0","198":"iin","199":"isi","200":"nal","201":"ndu","202":"ghj","203":"tii","204":"fa","205":"pri","206":"ev","207":"ssi","208":"ag","209":"p\u00f2","210":"atu","211":"ai","212":"et","213":"ipa","214":"\u00e8d","215":"iar","216":"ssa","217":"ah","218":"ica","219":"uv","220":"ona","221":"\u00f9n","222":"mod","223":"\u00e8i","224":"au","225":"rso","226":"gli","227":"ns","228":"ili","229":"ici","230":"ol","231":"nn","232":"qu","233":"adi","234":"l\u2019a","235":"cun","236":"asi","237":"ie","238":"nc","239":"fi","240":"ini","241":"ch\u00ec","242":"sp","243":"ori","244":"dii","245":"uni","246":"le","247":"c\u00f9","248":"cc","249":"int","250":"za","251":"con","252":"ber","253":"de","254":"gni","255":"ett","256":"nic","257":"lid","258":"llu","259":"tru","260":"lli","261":"inl","262":"lib","263":"anu","264":"ran","265":"lit","266":"cus","267":"iba","268":"omu","269":"ent","270":"ess","271":"naz","272":"tid","273":"imu","274":"ami","275":"iso","276":"nis","277":"a\u00e8","278":"oi","279":"vu","280":"ce","281":"co","282":"ug","283":"\u00e0s","284":"oa","285":"os","286":"zz","287":"r\u00e0","288":"\u2019o","289":"cr","290":"ach","291":"imo","292":"uar","293":"pru","294":"po","295":"ari","296":"tar","297":"ind","298":"enz","299":"ign","300":"\u00e0in","301":"inu","302":"acu","303":"se","304":"cum","305":"mp","306":"isp","307":"oc","308":"ati","309":"rc","310":"iss","311":"ni\u00e8","312":"rim","313":"fu","314":"ub","315":"sic","316":"evi","317":"t\u00e0d","318":"lia","319":"apa","320":"\u00e0p","321":"\u00e0l","322":"las","323":"ju","324":"tat","325":"ba","326":"ust","327":"pp","328":"tu\u00e0","329":"rr","330":"end","331":"isc","332":"sta","333":"to","334":"nud","335":"din","336":"uli","337":"ao","338":"n\u2019","339":"asu","340":"lo","341":"cia","342":"ist","343":"uog","344":"inc","345":"usi","346":"ro","347":"mb","348":"nio","349":"nim","350":"na\u00e0","351":"pae","352":"son","353":"alu","354":"var","355":"nza","356":"\u00e8s","357":"ipu","358":"iad","359":"cit","360":"ae","361":"em","362":"apr","363":"nda","364":"sia","365":"nid","366":"f\u00e0","367":"ina","368":"uti","369":"dic","370":"\u00e8c","371":"vol","372":"suc","373":"svi","374":"op","375":"sig","376":"nam","377":"ntr","378":"riv","379":"izi","380":"zzi","381":"tud","382":"ian","383":"idu","384":"\u2019om","385":"lus","386":"ita","387":"uri","388":"duc","389":"ara","390":"aas","391":"eg","392":"ah\u00e8","393":"ip\u00f2","394":"s\u2019e","395":"pin","396":"ivi","397":"ric","398":"ias","399":"aso","400":"dar","401":"min","402":"ipr","403":"gg","404":"utu","405":"emb","406":"mis","407":"ert","408":"ziu","409":"und","410":"\u2019i","411":"nta","412":"lic","413":"tit","414":"raz","415":"ed","416":"i\u00f2","417":"utt","418":"dim","419":"ubl","420":"\u00e0f","421":"cen","422":"a\u00e0","423":"h\u00ect","424":"hju","425":"ibe","426":"hi","427":"man","428":"\u00e8di","429":"sf","430":"uh\u00e0","431":"nit","432":"tra","433":"dia","434":"fun","435":"occ","436":"\u00e8\u00e0","437":"no","438":"chj","439":"uci","440":"dis","441":"rt\u00e0","442":"cur","443":"rid","444":"nno","445":"aru","446":"i\u00f9","447":"opu","448":"iap","449":"\u00e8u","450":"uma","451":"lig","452":"\u00e0e","453":"uso","454":"avi","455":"ana","456":"m\u2019","457":"dev","458":"jus","459":"imi","460":"\u00f9nh","461":"cip","462":"lah","463":"\u00ec\u00f9","464":"agh","465":"lop","466":"div","467":"vul","468":"unu","469":"dat","470":"itr","471":"hja","472":"fe","473":"ria","474":"gnu","475":"c\u00f9l","476":"umu","477":"ve","478":"nia","479":"\u2019av","480":"t\u00f9","481":"\u00e0un","482":"rad","483":"egg","484":"af","485":"ti\u00e8","486":"bi","487":"ern","488":"n\u00e8","489":"\u2019is","490":"i\u00f2c","491":"hjo","492":"ste","493":"sod","494":"upi","495":"d\u2019e","496":"\u00e0\u00e8\u00e0","497":"tif","498":"ue","499":"ru\u00e0","500":"tur","501":"li\u00e8","502":"ral","503":"nas","504":"lud","505":"odu","506":"cis","507":"asf","508":"\u00e8t","509":"mur","510":"dui","511":"ndi","512":"nqu","513":"api","514":"pe","515":"ura","516":"aal","517":"jo","518":"qui","519":"\u00e0g","520":"ren","521":"ain","522":"dif","523":"tes","524":"\u00e0pa","525":"ult","526":"\u00ecc","527":"ntu","528":"\u00f9u","529":"rut","530":"nf","531":"upa","532":"bl","533":"up\u00f2","534":"\u00e8ch","535":"\u00e8m","536":"bar","537":"itu","538":"\u00e0\u00e8","539":"lis","540":"a\u2019","541":"ute","542":"u\u00e0a","543":"nd\u2019","544":"sar","545":"att","546":"tis","547":"\u2019ed","548":"uca","549":"gi","550":"lup","551":"ul\u2019","552":"rn","553":"iid","554":"ris","555":"ani","556":"uda","557":"ssu","558":"ide","559":"mat","560":"\u00e0n","561":"uf","562":"ver","563":"unn","564":"ar\u00e0","565":"uun","566":"pac","567":"sip","568":"ciu","569":"sch","570":"iqu","571":"ast","572":"for","573":"ima","574":"osu","575":"rv","576":"ncu","577":"urm","578":"sot","579":"\u00e0o","580":"qua","581":"lin","582":"ucu","583":"\u00e8a","584":"den","585":"zaa","586":"\u00e0as","587":"\u00f9l","588":"sio","589":"\u00f2o","590":"ur\u00e0","591":"rvi","592":"tip","593":"gua","594":"cal","595":"adu","596":"alt","597":"ril","598":"chi","599":"nsa","600":"\u00eca","601":"iou","602":"vag","603":"ies","604":"pul","605":"liu","606":"aes","607":"s\u00f2p","608":"tem","609":"oal","610":"cam","611":"a\u00e0u","612":"tun","613":"s\u2019","614":"azz","615":"r\u00e0t","616":"ceg","617":"aad","618":"ava","619":"unc","620":"opa","621":"\u00e0og","622":"iif","623":"rii","624":"inf","625":"ic\u00f9","626":"spr","627":"nah","628":"ass","629":"sap","630":"\u00e0es","631":"nt\u00e0","632":"\u00e0us","633":"ou","634":"soi","635":"rip","636":"an\u00e8","637":"sof","638":"sin","639":"n\u2019s","640":"dul","641":"tuq","642":"vis","643":"aog","644":"dum","645":"and","646":"oin","647":"suu","648":"sad","649":"ru\u00e8","650":"pie","651":"pos","652":"l\u2019e","653":"iis","654":"arc","655":"lim","656":"das","657":"lio","658":"tri","659":"fig","660":"ipi","661":"igh","662":"mbi","663":"iva","664":"bli","665":"ame","666":"uod","667":"mun","668":"siu","669":"tuo","670":"ltr","671":"sun","672":"duu","673":"iz\u00e0","674":"p\u00f2e","675":"un\u2019","676":"ltu","677":"ont","678":"ten","679":"ibu","680":"due","681":"dig","682":"aar","683":"mul","684":"tta","685":"sop","686":"orz","687":"uad","688":"unq","689":"ual","690":"aco","691":"ael","692":"tet","693":"ico","694":"ugn","695":"d\u2019o","696":"sil","697":"rud","698":"\u00e0t","699":"ruc","700":"diu","701":"sis","702":"uan","703":"zii","704":"laa","705":"duv","706":"sti","707":"emp","708":"\u00e8cu","709":"ata","710":"otu","711":"scr","712":"run","713":"sat","714":"ret","715":"\u00f2c","716":"ade","717":"ure","718":"\u2019ac","719":"his","720":"cid","721":"luh","722":"d\u00ec","723":"nus","724":"\u00e8il","725":"til","726":"ant","727":"\u2019ai","728":"tim","729":"\u00e0pi","730":"amp","731":"\u00e0f\u00e0","732":"\u00e0\u00e0i","733":"he","734":"nla","735":"alo","736":"\u00e0up","737":"do","738":"sv","739":"dam","740":"gr","741":"\u2019u","742":"v\u00e8","743":"\u00e8g","744":"dav","745":"eru","746":"ez","747":"rov","748":"nup","749":"zu","750":"uel","751":"eme","752":"ng","753":"ri\u00e8","754":"cu\u00e8","755":"ih","756":"\u00e8li","757":"nad","758":"aid","759":"\u00e8un","760":"ume","761":"rri","762":"tal","763":"ifi","764":"if\u00e0","765":"nni","766":"\u00f9nc","767":"tac","768":"ta\u00e8","769":"ivu","770":"h\u00e8r","771":"h\u00eca","772":"\u00e8gh","773":"ov","774":"umo","775":"\u00f2p","776":"tiz","777":"nq","778":"ot","779":"ied","780":"igl","781":"s\u00f2","782":"\u2019s","783":"tad","784":"mon","785":"ga","786":"mai","787":"\u00e0si","788":"str","789":"nsi","790":"lu\u00f9","791":"\u00e0q","792":"dau","793":"upr","794":"nr","795":"des","796":"ida","797":"uns","798":"iac","799":"aut","800":"dip","801":"isa","802":"uva","803":"z\u00e0","804":"lad","805":"agi","806":"pop","807":"uq","808":"atr","809":"i\u00e8\u00e0","810":"i\u00e8a","811":"era","812":"\u00e0c\u00f9","813":"\u00e0um","814":"jon","815":"nm","816":"u\u00f9","817":"vo","818":"\u00e8p","819":"tel","820":"br","821":"niu","822":"nul","823":"rat","824":"ocu","825":"did","826":"\u2019or","827":"\u00e8l\u2019","828":"sol","829":"\u00e8so","830":"unl","831":"fu\u00e0","832":"u\u00e0d","833":"sso","834":"cif","835":"mid","836":"nuc","837":"oci","838":"bas","839":"abi","840":"va\u00e8","841":"spa","842":"tie","843":"iut","844":"i\u00e8r","845":"rgh","846":"jas","847":"\u00e8d\u2019","848":"ive","849":"\u00e0su","850":"\u00e8gu","851":"iih","852":"\u00f9as","853":"rci","854":"ave","855":"\u00e0ch","856":"erm","857":"ruh","858":"a\u00e0g","859":"av\u00e8","860":"gna","861":"soc","862":"cel","863":"i\u00e0i","864":"aav","865":"t\u00e0c","866":"\u00e0id","867":"cil","868":"esu","869":"can","870":"tan","871":"rua","872":"ese","873":"pif","874":"\u00e0\u00e0a","875":"c\u00e0r","876":"izz","877":"ffa","878":"\u00e0tr","879":"rsu","880":"zi\u00e0","881":"f\u00e0u","882":"us\u2019","883":"rel","884":"mal","885":"\u00f9is","886":"\u00ecin","887":"ice","888":"vie","889":"arp","890":"\u00e0ap","891":"men","892":"\u00f9nn","893":"dun","894":"opr","895":"ngr","896":"upp","897":"sen","898":"uoa","899":"ola","900":"iit","901":"vid","902":"uuu","903":"ube","904":"rup","905":"jal","906":"cir","907":"egh","908":"a\u00e0p","909":"aat","910":"tiv","911":"\u00e8fu","912":"od\u2019","913":"lem","914":"t\u00e0p","915":"ac\u00f9","916":"iaf","917":"usc","918":"\u00e0sp","919":"i\u00f9p","920":"ova","921":"sce","922":"\u00e8\u00e0a","923":"m\u2019\u00e8","924":"li\u00e0","925":"bin","926":"ucr","927":"up\u00e0","928":"\u2019au","929":"nde","930":"\u00ecch","931":"cai","932":"uic","933":"llo","934":"i\u00e0d","935":"val","936":"i\u00e8i","937":"\u00e0d\u2019","938":"n\u00e0a","939":"uoi","940":"uut","941":"iuc","942":"ins","943":"c\u00f9u","944":"z\u00e0c","945":"pus","946":"apu","947":"ang","948":"d\u2019i","949":"lao","950":"aca","951":"pit","952":"h\u00e8l","953":"d\u00ecc","954":"tuu","955":"aoa","956":"put","957":"t\u00e0f","958":"l\u2019u","959":"is\u2019","960":"rga","961":"f\u00e0c","962":"\u00e8im","963":"ezi","964":"\u00e0sc","965":"ud\u00e8","966":"aur","967":"otr","968":"ann","969":"lil","970":"u\u00e0s","971":"uuf","972":"acc","973":"ard","974":"uam","975":"gru","976":"ppi","977":"cuu","978":"ior","979":"amm","980":"osi","981":"arm","982":"usf","983":"\u2019im","984":"ife","985":"ena","986":"ppu","987":"ilo","988":"usv","989":"rus","990":"f\u00e0l","991":"nti","992":"agl","993":"\u00e0ad","994":"vip","995":"iuo","996":"a\u2019c","997":"nin","998":"rav","999":"u\u00e8c","1000":"diz","1001":"lme","1002":"urr","1003":"igr","1004":"upo","1005":"p\u00e0c","1006":"mig","1007":"cco","1008":"rih","1009":"rli","1010":"\u00e8ub","1011":"cni","1012":"mez","1013":"fis","1014":"i\u00e0g","1015":"u\u00ecc","1016":"\u00e0li","1017":"\u00f9l\u2019","1018":"lu\u00e0","1019":"ucc","1020":"tu\u00e8","1021":"lti","1022":"stu","1023":"aiu","1024":"\u2019ip","1025":"toc","1026":"\u00ecde","1027":"nzi","1028":"vut","1029":"h\u00e8e","1030":"iao","1031":"\u00f9uv","1032":"rar","1033":"ite","1034":"uzz","1035":"iuv","1036":"\u00ecna","1037":"\u00ecas","1038":"p\u00f2p","1039":"tir","1040":"\u00e8ma","1041":"\u00e0ud","1042":"uto","1043":"\u00e0\u00e8t","1044":"ob","1045":"r\u00e0i","1046":"rop","1047":"\u00e0\u00e0t","1048":"nuf","1049":"\u00e8n","1050":"tiu","1051":"une","1052":"\u00e0ci","1053":"nor","1054":"puu","1055":"hii","1056":"ofa","1057":"pub","1058":"eri","1059":"erd","1060":"nuh","1061":"cap","1062":"vit","1063":"uno","1064":"mic","1065":"res","1066":"rug","1067":"ip\u00e0","1068":"\u00e0go","1069":"rag","1070":"u\u00f9n","1071":"dad","1072":"rma","1073":"afo","1074":"ih\u00e8","1075":"a\u00e0s","1076":"ii\u00e0","1077":"sus","1078":"iec","1079":"\u00e8\u00e0u","1080":"mp\u00e0","1081":"\u00e8\u00e0l","1082":"sir","1083":"zid","1084":"t\u00e0h","1085":"jic","1086":"ome","1087":"\u2019\u00e8m","1088":"ais","1089":"ruv","1090":"iog","1091":"\u00e0d\u00ec","1092":"por","1093":"tau","1094":"tul","1095":"usa","1096":"uc\u00e0","1097":"cua","1098":"ec","1099":"rch","1100":"lip","1101":"\u2019in","1102":"i\u00e8t","1103":"urg","1104":"saz","1105":"l\u00e0","1106":"u\u00e8l","1107":"ni\u00e0","1108":"p\u00e0u","1109":"pet","1110":"\u00e8pi","1111":"u\u00e0p","1112":"\u00e0po","1113":"cui","1114":"\u00e8in","1115":"ter","1116":"\u00e0im","1117":"iip","1118":"rc\u00e0","1119":"\u2019\u00e8f","1120":"sss","1121":"of","1122":"san","1123":"uid","1124":"u\u00e8i","1125":"\u00e0fu","1126":"uch","1127":"\u00ecpa","1128":"z\u00e0i","1129":"\u00ecb","1130":"sal","1131":"h\u00e8d","1132":"\u00f9a","1133":"eac","1134":"np","1135":"t\u00e0s","1136":"\u2019c","1137":"jar","1138":"vir","1139":"pon","1140":"a\u00e8a","1141":"nur","1142":"pra","1143":"ad\u2019","1144":"cch","1145":"ezz","1146":"aod","1147":"sit","1148":"uaz","1149":"sif","1150":"sfa","1151":"zap","1152":"rb","1153":"tup","1154":"ugh","1155":"jur","1156":"cuo","1157":"iup","1158":"udu","1159":"vae","1160":"paa","1161":"iai","1162":"\u00ecu","1163":"bu","1164":"d\u2019u","1165":"i\u00e8p","1166":"cav","1167":"ne","1168":"\u2019\u00e8i","1169":"d\u2019\u00e8","1170":"ff","1171":"\u00e0\u00e0","1172":"nfi","1173":"asc","1174":"ei","1175":"\u00e8f","1176":"sse","1177":"\u00e0r","1178":"za\u00e8","1179":"\u00e0el","1180":"duf","1181":"dit","1182":"p\u00f2g","1183":"v\u00e0u","1184":"\u00ect","1185":"cn","1186":"\u00f2es","1187":"m\u00e0","1188":"anz","1189":"\u00f9al","1190":"\u00e0na","1191":"aun","1192":"dud","1193":"omi","1194":"arl","1195":"\u00e0\u00e8d","1196":"icr","1197":"eda","1198":"arr","1199":"tro","1200":"\u00e8da","1201":"emi","1202":"ser","1203":"\u00e8q","1204":"h\u00e8u","1205":"nap","1206":"\u00f2ch","1207":"pir","1208":"lta","1209":"zau","1210":"nab","1211":"pro","1212":"mem","1213":"bri","1214":"fam","1215":"iau","1216":"a\u00e8i","1217":"lc","1218":"lie","1219":"iq","1220":"rba","1221":"ia\u00e8","1222":"i\u00e0r","1223":"cii","1224":"uos","1225":"zze","1226":"\u00f2g","1227":"sih","1228":"jun","1229":"ngu","1230":"unt","1231":"d\u00e0","1232":"u\u00e0i","1233":"nai","1234":"l\u2019o","1235":"mi\u00e8","1236":"don","1237":"\u00e0sv","1238":"ilu","1239":"pp\u00e0","1240":"ugr","1241":"rd","1242":"usu","1243":"c\u00e0","1244":"unm","1245":"\u00f9bo","1246":"nui","1247":"\u00f9ma","1248":"\u00ecd","1249":"sui","1250":"\u2019ur","1251":"gan","1252":"\u00e8uv","1253":"ef","1254":"cre","1255":"\u2019\u00e8","1256":"pun","1257":"tre","1258":"mi\u00e0","1259":"\u00e0at","1260":"ira","1261":"a\u00e8l","1262":"\u2019up","1263":"rsa","1264":"ama","1265":"\u00f9b","1266":"i\u00f2d","1267":"uil","1268":"eii","1269":"\u00e8l","1270":"che","1271":"\u00ecp","1272":"rg","1273":"uip","1274":"uz","1275":"uop","1276":"fid","1277":"\u2019al","1278":"pis","1279":"nav","1280":"iag","1281":"hj\u00e0","1282":"\u00e8sc","1283":"egl","1284":"avo","1285":"dre","1286":"p\u00f2o","1287":"ala","1288":"ruu","1289":"u\u00e8v","1290":"esi","1291":"\u00e8pa","1292":"rsi","1293":"gui","1294":"h\u00e0u","1295":"\u00e0l\u2019","1296":"u\u00e8d","1297":"col","1298":"vin","1299":"ggi","1300":"lav","1301":"\u00e0ma","1302":"pi\u00f9","1303":"\u00f2c\u00e0","1304":"\u00ecq","1305":"h\u00e8s","1306":"ufa","1307":"luu","1308":"ven","1309":"n\u00e8i","1310":"ale","1311":"asa","1312":"let","1313":"in\u00e8","1314":"oun","1315":"oas","1316":"ono","1317":"ah\u00e0","1318":"ada","1319":"cev","1320":"\u00e0is","1321":"naa","1322":"sud","1323":"d\u2019a","1324":"v\u00e8i","1325":"nuu","1326":"\u00e8ad","1327":"onn","1328":"ase","1329":"a\u00e0a","1330":"t\u00e0o","1331":"u\u00ecu","1332":"naf","1333":"as\u00f2","1334":"odi","1335":"nlu","1336":"ufi","1337":"nch","1338":"\u00e8s\u2019","1339":"ogl","1340":"iiu","1341":"n\u2019p","1342":"et\u00e0","1343":"al\u2019","1344":"rta","1345":"uug","1346":"rca","1347":"tap","1348":"arv","1349":"aaz","1350":"\u00e0if","1351":"\u00e8ip","1352":"rin","1353":"tia","1354":"nun","1355":"\u2019pa","1356":"u\u00e0u","1357":"nan","1358":"t\u00e0\u00f9","1359":"vun","1360":"n\u00e8m","1361":"anc","1362":"\u00e0ni","1363":"lua","1364":"\u2019si","1365":"rna","1366":"nte","1367":"ioi","1368":"maa","1369":"\u2019sa","1370":"un\u00e8","1371":"tum","1372":"u\u00e0c","1373":"ioa","1374":"cru","1375":"del","1376":"vil","1377":"t\u00e0g","1378":"lar","1379":"aig","1380":"\u00e0al","1381":"\u00e8tu","1382":"u\u00e0e","1383":"u\u00e0q","1384":"h\u00ec\u00f9","1385":"nri","1386":"spi","1387":"lun","1388":"iav","1389":"mer","1390":"dr","1391":"ze","1392":"ud\u2019","1393":"mia","1394":"oc\u00f9","1395":"unp","1396":"gu","1397":"\u00e8v","1398":"ipe","1399":"ta\u00e0","1400":"t\u00f9\u00e8","1401":"t\u00e0\u00e8","1402":"rez","1403":"ab","1404":"lp","1405":"t\u00f9o","1406":"t\u00f9\u00f9","1407":"rui","1408":"bit","1409":"\u00e0qu","1410":"jam","1411":"a\u00e0f","1412":"\u2019un","1413":"\u00f2f","1414":"\u00e8st","1415":"pur","1416":"aap","1417":"lpe","1418":"dua","1419":"leg","1420":"gi\u00e8","1421":"ces","1422":"\u00f9m","1423":"sup","1424":"\u00e0av","1425":"civ","1426":"oli","1427":"nna","1428":"h\u00ecq","1429":"\u00f2fa","1430":"\u00f9ne","1431":"\u00e8nu","1432":"cau","1433":"am\u00e0","1434":"uoe","1435":"ffe","1436":"vu\u00e0","1437":"mpi","1438":"\u00f9nr","1439":"lir","1440":"nua","1441":"uzi","1442":"car","1443":"iat","1444":"luo","1445":"dup","1446":"oca","1447":"u\u00e8p","1448":"imp","1449":"arz","1450":"\u00ecdi","1451":"\u00e8ob","1452":"ifa","1453":"cri"},"freq_co":{"0":1479,"1":880,"2":802,"3":600,"4":592,"5":483,"6":463,"7":450,"8":387,"9":378,"10":306,"11":292,"12":249,"13":222,"14":178,"15":161,"16":138,"17":122,"18":117,"19":110,"20":106,"21":105,"22":95,"23":94,"24":93,"25":78,"26":74,"27":74,"28":71,"29":70,"30":70,"31":68,"32":65,"33":64,"34":59,"35":58,"36":57,"37":57,"38":56,"39":55,"40":52,"41":49,"42":47,"43":46,"44":43,"45":43,"46":40,"47":39,"48":37,"49":36,"50":36,"51":36,"52":35,"53":34,"54":33,"55":33,"56":33,"57":32,"58":32,"59":32,"60":32,"61":31,"62":31,"63":31,"64":31,"65":30,"66":29,"67":29,"68":28,"69":28,"70":28,"71":28,"72":27,"73":27,"74":27,"75":27,"76":27,"77":26,"78":26,"79":26,"80":26,"81":25,"82":25,"83":24,"84":24,"85":24,"86":24,"87":24,"88":24,"89":23,"90":23,"91":23,"92":23,"93":23,"94":23,"95":23,"96":23,"97":23,"98":23,"99":23,"100":23,"101":22,"102":22,"103":22,"104":22,"105":22,"106":21,"107":21,"108":21,"109":21,"110":21,"111":20,"112":20,"113":20,"114":19,"115":19,"116":19,"117":18,"118":18,"119":18,"120":18,"121":18,"122":18,"123":18,"124":17,"125":17,"126":17,"127":17,"128":17,"129":17,"130":17,"131":17,"132":16,"133":16,"134":15,"135":15,"136":15,"137":15,"138":14,"139":14,"140":14,"141":14,"142":14,"143":14,"144":14,"145":14,"146":14,"147":13,"148":13,"149":13,"150":13,"151":13,"152":13,"153":13,"154":13,"155":13,"156":13,"157":13,"158":13,"159":13,"160":12,"161":12,"162":12,"163":12,"164":12,"165":12,"166":12,"167":12,"168":12,"169":12,"170":11,"171":11,"172":11,"173":11,"174":11,"175":11,"176":11,"177":11,"178":11,"179":11,"180":11,"181":11,"182":11,"183":10,"184":10,"185":10,"186":10,"187":10,"188":10,"189":10,"190":10,"191":10,"192":10,"193":10,"194":10,"195":10,"196":10,"197":10,"198":10,"199":10,"200":10,"201":9,"202":9,"203":9,"204":9,"205":9,"206":9,"207":9,"208":9,"209":9,"210":9,"211":9,"212":9,"213":9,"214":9,"215":9,"216":9,"217":9,"218":9,"219":9,"220":9,"221":9,"222":9,"223":9,"224":9,"225":9,"226":8,"227":8,"228":8,"229":8,"230":8,"231":8,"232":8,"233":8,"234":8,"235":8,"236":8,"237":8,"238":8,"239":8,"240":8,"241":8,"242":8,"243":8,"244":8,"245":8,"246":8,"247":8,"248":8,"249":8,"250":8,"251":8,"252":8,"253":8,"254":7,"255":7,"256":7,"257":7,"258":7,"259":7,"260":7,"261":7,"262":7,"263":7,"264":7,"265":7,"266":7,"267":7,"268":7,"269":7,"270":7,"271":7,"272":7,"273":7,"274":7,"275":7,"276":7,"277":7,"278":7,"279":7,"280":7,"281":7,"282":7,"283":7,"284":7,"285":7,"286":7,"287":7,"288":7,"289":7,"290":6,"291":6,"292":6,"293":6,"294":6,"295":6,"296":6,"297":6,"298":6,"299":6,"300":6,"301":6,"302":6,"303":6,"304":6,"305":6,"306":6,"307":6,"308":6,"309":6,"310":6,"311":6,"312":6,"313":6,"314":6,"315":6,"316":6,"317":6,"318":6,"319":6,"320":6,"321":6,"322":6,"323":6,"324":6,"325":6,"326":6,"327":6,"328":5,"329":5,"330":5,"331":5,"332":5,"333":5,"334":5,"335":5,"336":5,"337":5,"338":5,"339":5,"340":5,"341":5,"342":5,"343":5,"344":5,"345":5,"346":5,"347":5,"348":5,"349":5,"350":5,"351":5,"352":5,"353":5,"354":5,"355":5,"356":5,"357":5,"358":5,"359":5,"360":5,"361":5,"362":5,"363":5,"364":5,"365":5,"366":5,"367":5,"368":5,"369":5,"370":5,"371":5,"372":4,"373":4,"374":4,"375":4,"376":4,"377":4,"378":4,"379":4,"380":4,"381":4,"382":4,"383":4,"384":4,"385":4,"386":4,"387":4,"388":4,"389":4,"390":4,"391":4,"392":4,"393":4,"394":4,"395":4,"396":4,"397":4,"398":4,"399":4,"400":4,"401":4,"402":4,"403":4,"404":4,"405":4,"406":4,"407":4,"408":4,"409":4,"410":4,"411":4,"412":4,"413":4,"414":4,"415":4,"416":4,"417":4,"418":4,"419":4,"420":4,"421":4,"422":4,"423":4,"424":4,"425":4,"426":4,"427":4,"428":4,"429":4,"430":4,"431":4,"432":4,"433":4,"434":4,"435":4,"436":4,"437":4,"438":4,"439":4,"440":4,"441":4,"442":3,"443":3,"444":3,"445":3,"446":3,"447":3,"448":3,"449":3,"450":3,"451":3,"452":3,"453":3,"454":3,"455":3,"456":3,"457":3,"458":3,"459":3,"460":3,"461":3,"462":3,"463":3,"464":3,"465":3,"466":3,"467":3,"468":3,"469":3,"470":3,"471":3,"472":3,"473":3,"474":3,"475":3,"476":3,"477":3,"478":3,"479":3,"480":3,"481":3,"482":3,"483":3,"484":3,"485":3,"486":3,"487":3,"488":3,"489":3,"490":3,"491":3,"492":3,"493":3,"494":3,"495":3,"496":3,"497":3,"498":3,"499":3,"500":3,"501":3,"502":3,"503":3,"504":3,"505":3,"506":3,"507":3,"508":3,"509":3,"510":3,"511":3,"512":3,"513":3,"514":3,"515":3,"516":3,"517":3,"518":3,"519":3,"520":3,"521":3,"522":3,"523":3,"524":3,"525":3,"526":3,"527":3,"528":3,"529":3,"530":3,"531":3,"532":3,"533":3,"534":3,"535":3,"536":3,"537":3,"538":3,"539":3,"540":3,"541":3,"542":3,"543":3,"544":3,"545":3,"546":3,"547":3,"548":3,"549":3,"550":3,"551":3,"552":3,"553":3,"554":3,"555":3,"556":3,"557":3,"558":3,"559":3,"560":3,"561":3,"562":3,"563":3,"564":2,"565":2,"566":2,"567":2,"568":2,"569":2,"570":2,"571":2,"572":2,"573":2,"574":2,"575":2,"576":2,"577":2,"578":2,"579":2,"580":2,"581":2,"582":2,"583":2,"584":2,"585":2,"586":2,"587":2,"588":2,"589":2,"590":2,"591":2,"592":2,"593":2,"594":2,"595":2,"596":2,"597":2,"598":2,"599":2,"600":2,"601":2,"602":2,"603":2,"604":2,"605":2,"606":2,"607":2,"608":2,"609":2,"610":2,"611":2,"612":2,"613":2,"614":2,"615":2,"616":2,"617":2,"618":2,"619":2,"620":2,"621":2,"622":2,"623":2,"624":2,"625":2,"626":2,"627":2,"628":2,"629":2,"630":2,"631":2,"632":2,"633":2,"634":2,"635":2,"636":2,"637":2,"638":2,"639":2,"640":2,"641":2,"642":2,"643":2,"644":2,"645":2,"646":2,"647":2,"648":2,"649":2,"650":2,"651":2,"652":2,"653":2,"654":2,"655":2,"656":2,"657":2,"658":2,"659":2,"660":2,"661":2,"662":2,"663":2,"664":2,"665":2,"666":2,"667":2,"668":2,"669":2,"670":2,"671":2,"672":2,"673":2,"674":2,"675":2,"676":2,"677":2,"678":2,"679":2,"680":2,"681":2,"682":2,"683":2,"684":2,"685":2,"686":2,"687":2,"688":2,"689":2,"690":2,"691":2,"692":2,"693":2,"694":2,"695":2,"696":2,"697":2,"698":2,"699":2,"700":2,"701":2,"702":2,"703":2,"704":2,"705":2,"706":2,"707":2,"708":2,"709":2,"710":2,"711":2,"712":2,"713":2,"714":2,"715":2,"716":2,"717":2,"718":2,"719":2,"720":2,"721":2,"722":2,"723":2,"724":2,"725":2,"726":2,"727":2,"728":2,"729":2,"730":2,"731":2,"732":2,"733":2,"734":2,"735":2,"736":2,"737":2,"738":2,"739":2,"740":2,"741":2,"742":2,"743":2,"744":2,"745":2,"746":2,"747":2,"748":2,"749":2,"750":2,"751":2,"752":2,"753":2,"754":2,"755":2,"756":2,"757":2,"758":2,"759":2,"760":2,"761":2,"762":2,"763":2,"764":2,"765":2,"766":2,"767":2,"768":2,"769":2,"770":2,"771":2,"772":2,"773":2,"774":2,"775":2,"776":2,"777":2,"778":2,"779":2,"780":2,"781":2,"782":2,"783":2,"784":2,"785":2,"786":2,"787":2,"788":2,"789":2,"790":2,"791":2,"792":2,"793":2,"794":2,"795":2,"796":2,"797":2,"798":2,"799":2,"800":2,"801":2,"802":2,"803":2,"804":2,"805":2,"806":2,"807":2,"808":2,"809":2,"810":2,"811":2,"812":2,"813":2,"814":2,"815":2,"816":2,"817":2,"818":2,"819":2,"820":2,"821":2,"822":2,"823":2,"824":2,"825":2,"826":1,"827":1,"828":1,"829":1,"830":1,"831":1,"832":1,"833":1,"834":1,"835":1,"836":1,"837":1,"838":1,"839":1,"840":1,"841":1,"842":1,"843":1,"844":1,"845":1,"846":1,"847":1,"848":1,"849":1,"850":1,"851":1,"852":1,"853":1,"854":1,"855":1,"856":1,"857":1,"858":1,"859":1,"860":1,"861":1,"862":1,"863":1,"864":1,"865":1,"866":1,"867":1,"868":1,"869":1,"870":1,"871":1,"872":1,"873":1,"874":1,"875":1,"876":1,"877":1,"878":1,"879":1,"880":1,"881":1,"882":1,"883":1,"884":1,"885":1,"886":1,"887":1,"888":1,"889":1,"890":1,"891":1,"892":1,"893":1,"894":1,"895":1,"896":1,"897":1,"898":1,"899":1,"900":1,"901":1,"902":1,"903":1,"904":1,"905":1,"906":1,"907":1,"908":1,"909":1,"910":1,"911":1,"912":1,"913":1,"914":1,"915":1,"916":1,"917":1,"918":1,"919":1,"920":1,"921":1,"922":1,"923":1,"924":1,"925":1,"926":1,"927":1,"928":1,"929":1,"930":1,"931":1,"932":1,"933":1,"934":1,"935":1,"936":1,"937":1,"938":1,"939":1,"940":1,"941":1,"942":1,"943":1,"944":1,"945":1,"946":1,"947":1,"948":1,"949":1,"950":1,"951":1,"952":1,"953":1,"954":1,"955":1,"956":1,"957":1,"958":1,"959":1,"960":1,"961":1,"962":1,"963":1,"964":1,"965":1,"966":1,"967":1,"968":1,"969":1,"970":1,"971":1,"972":1,"973":1,"974":1,"975":1,"976":1,"977":1,"978":1,"979":1,"980":1,"981":1,"982":1,"983":1,"984":1,"985":1,"986":1,"987":1,"988":1,"989":1,"990":1,"991":1,"992":1,"993":1,"994":1,"995":1,"996":1,"997":1,"998":1,"999":1,"1000":1,"1001":1,"1002":1,"1003":1,"1004":1,"1005":1,"1006":1,"1007":1,"1008":1,"1009":1,"1010":1,"1011":1,"1012":1,"1013":1,"1014":1,"1015":1,"1016":1,"1017":1,"1018":1,"1019":1,"1020":1,"1021":1,"1022":1,"1023":1,"1024":1,"1025":1,"1026":1,"1027":1,"1028":1,"1029":1,"1030":1,"1031":1,"1032":1,"1033":1,"1034":1,"1035":1,"1036":1,"1037":1,"1038":1,"1039":1,"1040":1,"1041":1,"1042":1,"1043":1,"1044":1,"1045":1,"1046":1,"1047":1,"1048":1,"1049":1,"1050":1,"1051":1,"1052":1,"1053":1,"1054":1,"1055":1,"1056":1,"1057":1,"1058":1,"1059":1,"1060":1,"1061":1,"1062":1,"1063":1,"1064":1,"1065":1,"1066":1,"1067":1,"1068":1,"1069":1,"1070":1,"1071":1,"1072":1,"1073":1,"1074":1,"1075":1,"1076":1,"1077":1,"1078":1,"1079":1,"1080":1,"1081":1,"1082":1,"1083":1,"1084":1,"1085":1,"1086":1,"1087":1,"1088":1,"1089":1,"1090":1,"1091":1,"1092":1,"1093":1,"1094":1,"1095":1,"1096":1,"1097":1,"1098":1,"1099":1,"1100":1,"1101":1,"1102":1,"1103":1,"1104":1,"1105":1,"1106":1,"1107":1,"1108":1,"1109":1,"1110":1,"1111":1,"1112":1,"1113":1,"1114":1,"1115":1,"1116":1,"1117":1,"1118":1,"1119":1,"1120":1,"1121":1,"1122":1,"1123":1,"1124":1,"1125":1,"1126":1,"1127":1,"1128":1,"1129":1,"1130":1,"1131":1,"1132":1,"1133":1,"1134":1,"1135":1,"1136":1,"1137":1,"1138":1,"1139":1,"1140":1,"1141":1,"1142":1,"1143":1,"1144":1,"1145":1,"1146":1,"1147":1,"1148":1,"1149":1,"1150":1,"1151":1,"1152":1,"1153":1,"1154":1,"1155":1,"1156":1,"1157":1,"1158":1,"1159":1,"1160":1,"1161":1,"1162":1,"1163":1,"1164":1,"1165":1,"1166":1,"1167":1,"1168":1,"1169":1,"1170":1,"1171":1,"1172":1,"1173":1,"1174":1,"1175":1,"1176":1,"1177":1,"1178":1,"1179":1,"1180":1,"1181":1,"1182":1,"1183":1,"1184":1,"1185":1,"1186":1,"1187":1,"1188":1,"1189":1,"1190":1,"1191":1,"1192":1,"1193":1,"1194":1,"1195":1,"1196":1,"1197":1,"1198":1,"1199":1,"1200":1,"1201":1,"1202":1,"1203":1,"1204":1,"1205":1,"1206":1,"1207":1,"1208":1,"1209":1,"1210":1,"1211":1,"1212":1,"1213":1,"1214":1,"1215":1,"1216":1,"1217":1,"1218":1,"1219":1,"1220":1,"1221":1,"1222":1,"1223":1,"1224":1,"1225":1,"1226":1,"1227":1,"1228":1,"1229":1,"1230":1,"1231":1,"1232":1,"1233":1,"1234":1,"1235":1,"1236":1,"1237":1,"1238":1,"1239":1,"1240":1,"1241":1,"1242":1,"1243":1,"1244":1,"1245":1,"1246":1,"1247":1,"1248":1,"1249":1,"1250":1,"1251":1,"1252":1,"1253":1,"1254":1,"1255":1,"1256":1,"1257":1,"1258":1,"1259":1,"1260":1,"1261":1,"1262":1,"1263":1,"1264":1,"1265":1,"1266":1,"1267":1,"1268":1,"1269":1,"1270":1,"1271":1,"1272":1,"1273":1,"1274":1,"1275":1,"1276":1,"1277":1,"1278":1,"1279":1,"1280":1,"1281":1,"1282":1,"1283":1,"1284":1,"1285":1,"1286":1,"1287":1,"1288":1,"1289":1,"1290":1,"1291":1,"1292":1,"1293":1,"1294":1,"1295":1,"1296":1,"1297":1,"1298":1,"1299":1,"1300":1,"1301":1,"1302":1,"1303":1,"1304":1,"1305":1,"1306":1,"1307":1,"1308":1,"1309":1,"1310":1,"1311":1,"1312":1,"1313":1,"1314":1,"1315":1,"1316":1,"1317":1,"1318":1,"1319":1,"1320":1,"1321":1,"1322":1,"1323":1,"1324":1,"1325":1,"1326":1,"1327":1,"1328":1,"1329":1,"1330":1,"1331":1,"1332":1,"1333":1,"1334":1,"1335":1,"1336":1,"1337":1,"1338":1,"1339":1,"1340":1,"1341":1,"1342":1,"1343":1,"1344":1,"1345":1,"1346":1,"1347":1,"1348":1,"1349":1,"1350":1,"1351":1,"1352":1,"1353":1,"1354":1,"1355":1,"1356":1,"1357":1,"1358":1,"1359":1,"1360":1,"1361":1,"1362":1,"1363":1,"1364":1,"1365":1,"1366":1,"1367":1,"1368":1,"1369":1,"1370":1,"1371":1,"1372":1,"1373":1,"1374":1,"1375":1,"1376":1,"1377":1,"1378":1,"1379":1,"1380":1,"1381":1,"1382":1,"1383":1,"1384":1,"1385":1,"1386":1,"1387":1,"1388":1,"1389":1,"1390":1,"1391":1,"1392":1,"1393":1,"1394":1,"1395":1,"1396":1,"1397":1,"1398":1,"1399":1,"1400":1,"1401":1,"1402":1,"1403":1,"1404":1,"1405":1,"1406":1,"1407":1,"1408":1,"1409":1,"1410":1,"1411":1,"1412":1,"1413":1,"1414":1,"1415":1,"1416":1,"1417":1,"1418":1,"1419":1,"1420":1,"1421":1,"1422":1,"1423":1,"1424":1,"1425":1,"1426":1,"1427":1,"1428":1,"1429":1,"1430":1,"1431":1,"1432":1,"1433":1,"1434":1,"1435":1,"1436":1,"1437":1,"1438":1,"1439":1,"1440":1,"1441":1,"1442":1,"1443":1,"1444":1,"1445":1,"1446":1,"1447":1,"1448":1,"1449":1,"1450":1,"1451":1,"1452":1,"1453":1}}